rxts_trading_sdk-0.1.3.dist-info/licenses/LICENSE
trading_sdk/__init__.py
trading_sdk/callbacks.py
trading_sdk/client_bus.py
trading_sdk/config.py
trading_sdk/global_pb2.py
trading_sdk/interfaces.py
trading_sdk/logger.py
trading_sdk/main.py
trading_sdk/market_data_monitor.py
trading_sdk/market_data_pb2.py
trading_sdk/message_seq_manager.py
trading_sdk/socket_transport.py
rxts_trading_sdk-0.1.3.dist-info/METADATA
rxts_trading_sdk-0.1.3.dist-info/WHEEL
rxts_trading_sdk-0.1.3.dist-info/top_level.txt
rxts_trading_sdk-0.1.3.dist-info/RECORD
