Metadata-Version: 2.4
Name: rxts-trading-sdk
Version: 0.1.3
Summary: RXTS Trading SDK
Author-email: JasonJiang0303 <chinese88+0303@2925.com>
License-Expression: MIT
Project-URL: Homepage, https://github.com/JasonJiang0303/rxts-trading-sdk
Project-URL: Bug Tracker, https://github.com/JasonJiang0303/rxts-trading-sdk/issues
Classifier: Programming Language :: Python :: 3
Classifier: Operating System :: OS Independent
Requires-Python: >=3.8
License-File: LICENSE
Requires-Dist: protobuf>=3.19.0
Requires-Dist: pyyaml>=6.0
Requires-Dist: watchdog>=2.1.9
Requires-Dist: l2data-reader>=0.1.18
Requires-Dist: level2-order-book>=0.1.1
Dynamic: license-file
